tsadf/__init__.py
tsadf/anomalydetection.py
tsadf/framework.py
tsadf/main.py
tsadf/timedataframe.py
tsadf/utility.py
tsadf_pieterhop-0.0.1.dist-info/LICENSE.txt
tsadf_pieterhop-0.0.1.dist-info/METADATA
tsadf_pieterhop-0.0.1.dist-info/WHEEL
tsadf_pieterhop-0.0.1.dist-info/top_level.txt
tsadf_pieterhop-0.0.1.dist-info/RECORD
